[
    {
        "ht7": 0, 
        "againstTrump": 0, 
        "ranking_score": 0.027584712933981476, 
        "againstClinton": 0, 
        "text": "#imwithher https://t.co/zgCUqknO2R With recent Revelations, Where is the Outrage from the Trump people? actually for all Americans who wan\u2026", 
        "created_at": "Sat Oct 01 08:00:09 +0000 2016", 
        "favorClinton": 1, 
        "location": "not hiding from accountability", 
        "tokens": [
            "recent", 
            "revelation", 
            "outrage", 
            "trump", 
            "people", 
            "actually", 
            "american", 
            "wan"
        ], 
        "ht6": 0, 
        "ht5": 0, 
        "ht4": 0, 
        "ht3": 1, 
        "ht2": 0, 
        "ht1": 0, 
        "user_id": "760863213483327489", 
        "retweet_count": 0, 
        "id": 345956188321919757, 
        "favorTrump": 0, 
        "ht8": 0
    }, 
    {
        "ht7": 0, 
        "againstTrump": 0, 
        "ranking_score": 0.038460722648635426, 
        "againstClinton": 0, 
        "text": "Trump About You #realdonaldtrump #trump2016 #WisconsinPrimary https://t.co/j58e8aacrE #VoteTrump2016 #A2 #tcot #A1 https://t.co/OxWxE22D7G", 
        "created_at": "Sat Oct 01 08:00:45 +0000 2016", 
        "favorClinton": 0, 
        "location": "New Jersey, USA", 
        "tokens": [
            "trump"
        ], 
        "ht6": 0, 
        "ht5": 0, 
        "ht4": 0, 
        "ht3": 0, 
        "ht2": 0, 
        "ht1": 1, 
        "user_id": "449110269", 
        "retweet_count": 0, 
        "id": 5072921095345316308, 
        "favorTrump": 1, 
        "ht8": 0
    }, 
    {
        "ht7": 0, 
        "againstTrump": 0, 
        "ranking_score": 0.03845976020020239, 
        "againstClinton": 0, 
        "text": "#realdonaldtrump American Nightmares #military #army #navy #usmc #airforce #veterans #trump #trumptrain #trump2016 https://t.co/SbTwsmn98p", 
        "created_at": "Sat Oct 01 08:01:04 +0000 2016", 
        "favorClinton": 0, 
        "location": "New Jersey, USA", 
        "tokens": [
            "american", 
            "nightmare"
        ], 
        "ht6": 0, 
        "ht5": 0, 
        "ht4": 0, 
        "ht3": 0, 
        "ht2": 0, 
        "ht1": 1, 
        "user_id": "449110269", 
        "retweet_count": 0, 
        "id": 1826077905195505484, 
        "favorTrump": 1, 
        "ht8": 0
    }, 
    {
        "ht7": 0, 
        "againstTrump": 0, 
        "ranking_score": 0.11235455757547683, 
        "againstClinton": 0, 
        "text": "RT @amrightnow: #realdonaldtrump American Nightmares #military #army #navy #usmc #airforce #veterans #trump #trumptrain #trump2016 https://\u2026", 
        "created_at": "Sat Oct 01 08:01:28 +0000 2016", 
        "favorClinton": 0, 
        "location": "USA", 
        "tokens": [
            "american", 
            "nightmare"
        ], 
        "ht6": 0, 
        "ht5": 0, 
        "ht4": 0, 
        "ht3": 0, 
        "ht2": 0, 
        "ht1": 1, 
        "user_id": "4821423943", 
        "retweet_count": 1, 
        "id": 2400210028226284579, 
        "favorTrump": 1, 
        "ht8": 0
    }, 
    {
        "ht7": 0, 
        "againstTrump": 1, 
        "ranking_score": 0.8880285774549144, 
        "againstClinton": 0, 
        "text": "Hey @realDonaldTrump Its 3:00 am wake up !!! and take what you take to be awake, and tweet \ud83d\udca9\ud83d\udebd #nevertrump", 
        "created_at": "Sat Oct 01 08:01:34 +0000 2016", 
        "favorClinton": 0, 
        "location": null, 
        "tokens": [
            "hey", 
            "300", 
            "wake", 
            "take", 
            "take", 
            "awake", 
            "tweet"
        ], 
        "ht6": 0, 
        "ht5": 1, 
        "ht4": 0, 
        "ht3": 0, 
        "ht2": 0, 
        "ht1": 0, 
        "user_id": "732403922975870976", 
        "retweet_count": 0, 
        "id": 5309258302217007079, 
        "favorTrump": 0, 
        "ht8": 0
    }, 
    {
        "ht7": 0, 
        "againstTrump": 0, 
        "ranking_score": 0.34830681542272757, 
        "againstClinton": 0, 
        "text": "@realDonaldTrump  LOSER. You didn't win Where it really counts. You proved your not fit after this week. #imwithher\u2026 https://t.co/lx3GlpAeus", 
        "created_at": "Sat Oct 01 08:02:49 +0000 2016", 
        "favorClinton": 1, 
        "location": "Burlington, NJ", 
        "tokens": [
            "loser", 
            "win", 
            "really", 
            "count", 
            "proved", 
            "fit", 
            "week"
        ], 
        "ht6": 0, 
        "ht5": 0, 
        "ht4": 0, 
        "ht3": 1, 
        "ht2": 0, 
        "ht1": 0, 
        "user_id": "3359817124", 
        "retweet_count": 0, 
        "id": 3802662055075863486, 
        "favorTrump": 0, 
        "ht8": 0
    }, 
    {
        "ht7": 0, 
        "againstTrump": 0, 
        "ranking_score": 0.08278173320231498, 
        "againstClinton": 0, 
        "text": "Ford to build huge plant in Mexico despite outrage https://t.co/4qMisWjvwX #realDonaldTrump #trump2016 #maga https://t.co/RtTlOWEoDb", 
        "created_at": "Sat Oct 01 08:03:03 +0000 2016", 
        "favorClinton": 0, 
        "location": "USA", 
        "tokens": [
            "ford", 
            "build", 
            "huge", 
            "plant", 
            "mexico", 
            "despite", 
            "outrage"
        ], 
        "ht6": 0, 
        "ht5": 0, 
        "ht4": 0, 
        "ht3": 0, 
        "ht2": 0, 
        "ht1": 1, 
        "user_id": "4081892233", 
        "retweet_count": 0, 
        "id": 7878482920009323362, 
        "favorTrump": 1, 
        "ht8": 0
    }, 
    {
        "ht7": 0, 
        "againstTrump": 0, 
        "ranking_score": 0.3650761428757955, 
        "againstClinton": 0, 
        "text": "RT @amrightnow: Trump About You #realdonaldtrump #trump2016 #WisconsinPrimary https://t.co/j58e8aacrE #VoteTrump2016 #A2 #tcot #A1 https://\u2026", 
        "created_at": "Sat Oct 01 08:03:05 +0000 2016", 
        "favorClinton": 0, 
        "location": "LOVE GOD & COUNTRY ", 
        "tokens": [
            "trump"
        ], 
        "ht6": 0, 
        "ht5": 0, 
        "ht4": 0, 
        "ht3": 0, 
        "ht2": 0, 
        "ht1": 1, 
        "user_id": "1126012902", 
        "retweet_count": 1, 
        "id": 5517482588422754322, 
        "favorTrump": 1, 
        "ht8": 0
    }, 
    {
        "ht7": 0, 
        "againstTrump": 0, 
        "ranking_score": 0.21710619989893762, 
        "againstClinton": 0, 
        "text": "RT @EcuadorForTrump: #KidsForTrump know @HillaryClinton is #crookedhillary #latinosfortrump #latinowithtrump #trump2016 @realDonaldTrump ht\u2026", 
        "created_at": "Sat Oct 01 08:03:50 +0000 2016", 
        "favorClinton": 0, 
        "location": "Florida, USA", 
        "tokens": [
            "know"
        ], 
        "ht6": 0, 
        "ht5": 0, 
        "ht4": 0, 
        "ht3": 0, 
        "ht2": 0, 
        "ht1": 1, 
        "user_id": "709262824372117504", 
        "retweet_count": 13, 
        "id": 623991414343850291, 
        "favorTrump": 1, 
        "ht8": 0
    }, 
    {
        "ht7": 0, 
        "againstTrump": 0, 
        "ranking_score": 0.27227495957137565, 
        "againstClinton": 0, 
        "text": "RT @amrightnow: Trump About You #realdonaldtrump #trump2016 #WisconsinPrimary https://t.co/j58e8aacrE #VoteTrump2016 #A2 #tcot #A1 https://\u2026", 
        "created_at": "Sat Oct 01 08:04:14 +0000 2016", 
        "favorClinton": 0, 
        "location": "Michigan, USA", 
        "tokens": [
            "trump"
        ], 
        "ht6": 0, 
        "ht5": 0, 
        "ht4": 0, 
        "ht3": 0, 
        "ht2": 0, 
        "ht1": 1, 
        "user_id": "133005157", 
        "retweet_count": 2, 
        "id": 2190074602796116415, 
        "favorTrump": 1, 
        "ht8": 0
    }, 
    {
        "ht7": 0, 
        "againstTrump": 0, 
        "ranking_score": 1.1652891343957645, 
        "againstClinton": 0, 
        "text": "RT @TrumpedAmerica: Ford to build huge plant in Mexico despite outrage https://t.co/4qMisWjvwX #realDonaldTrump #trump2016 #maga https://t.\u2026", 
        "created_at": "Sat Oct 01 08:05:08 +0000 2016", 
        "favorClinton": 0, 
        "location": "Vero Beach, FL", 
        "tokens": [
            "ford", 
            "build", 
            "huge", 
            "plant", 
            "mexico", 
            "despite", 
            "outrage"
        ], 
        "ht6": 0, 
        "ht5": 0, 
        "ht4": 0, 
        "ht3": 0, 
        "ht2": 0, 
        "ht1": 1, 
        "user_id": "2405538056", 
        "retweet_count": 1, 
        "id": 3353569003514063373, 
        "favorTrump": 1, 
        "ht8": 0
    }, 
    {
        "ht7": 0, 
        "againstTrump": 0, 
        "ranking_score": 0.8725258809236699, 
        "againstClinton": 0, 
        "text": "RT @TrumpedAmerica: Trump About You https://t.co/AGxA2aMcL4 #TheRealDonaldTrump #trump2016 #TrumpTrain #VoteTrump2016 #2A #tcot https://t.c\u2026", 
        "created_at": "Sat Oct 01 08:06:09 +0000 2016", 
        "favorClinton": 0, 
        "location": "Henderson NV ", 
        "tokens": [
            "trump"
        ], 
        "ht6": 0, 
        "ht5": 0, 
        "ht4": 0, 
        "ht3": 0, 
        "ht2": 0, 
        "ht1": 1, 
        "user_id": "298731715", 
        "retweet_count": 1, 
        "id": 4339454032909713528, 
        "favorTrump": 1, 
        "ht8": 0
    }, 
    {
        "ht7": 0, 
        "againstTrump": 0, 
        "ranking_score": 5.519014223365886, 
        "againstClinton": 0, 
        "text": "This nails it - the best so far! #trump #lovetrumpshate #imwithher #hillaryclinton #election2016 #thisiseverything\u2026 https://t.co/UOZaALJaZC", 
        "created_at": "Sat Oct 01 08:06:17 +0000 2016", 
        "favorClinton": 1, 
        "location": "Stuttgart", 
        "tokens": [
            "nail", 
            "best", 
            "far"
        ], 
        "ht6": 0, 
        "ht5": 0, 
        "ht4": 0, 
        "ht3": 1, 
        "ht2": 0, 
        "ht1": 0, 
        "user_id": "255632730", 
        "retweet_count": 0, 
        "id": 284979626828814557, 
        "favorTrump": 0, 
        "ht8": 0
    }, 
    {
        "ht7": 0, 
        "againstTrump": 0, 
        "ranking_score": 1.3244917999291808, 
        "againstClinton": 0, 
        "text": "RT @TrumpedAmerica: Ford to build huge plant in Mexico despite outrage https://t.co/4qMisWjvwX #realDonaldTrump #trump2016 #maga https://t.\u2026", 
        "created_at": "Sat Oct 01 08:07:21 +0000 2016", 
        "favorClinton": 0, 
        "location": "Plantation, Broward, Florida", 
        "tokens": [
            "ford", 
            "build", 
            "huge", 
            "plant", 
            "mexico", 
            "despite", 
            "outrage"
        ], 
        "ht6": 0, 
        "ht5": 0, 
        "ht4": 0, 
        "ht3": 0, 
        "ht2": 0, 
        "ht1": 1, 
        "user_id": "171911873", 
        "retweet_count": 2, 
        "id": 686292758285657904, 
        "favorTrump": 1, 
        "ht8": 0
    }, 
    {
        "ht7": 0, 
        "againstTrump": 1, 
        "ranking_score": 0.5826156974109176, 
        "againstClinton": 0, 
        "text": "he said he won anyway so why would anyone care lol #dumptrump https://t.co/hZM9z5WKfF", 
        "created_at": "Sat Oct 01 08:07:48 +0000 2016", 
        "favorClinton": 0, 
        "location": "NYC- the only city", 
        "tokens": [
            "said", 
            "anyway", 
            "would", 
            "anyone", 
            "care", 
            "lol"
        ], 
        "ht6": 1, 
        "ht5": 0, 
        "ht4": 0, 
        "ht3": 0, 
        "ht2": 0, 
        "ht1": 0, 
        "user_id": "2190409926", 
        "retweet_count": 0, 
        "id": 6946651752147309753, 
        "favorTrump": 0, 
        "ht8": 0
    }, 
    {
        "ht7": 0, 
        "againstTrump": 0, 
        "ranking_score": 0.3200119020307628, 
        "againstClinton": 0, 
        "text": "#Trump2016  #makeamericagreatagain Voting For Hillary Clinton Equals Accelerating Muslim Killings Of Americans - https://t.co/ZJ7Kp7VXba", 
        "created_at": "Sat Oct 01 08:08:15 +0000 2016", 
        "favorClinton": 0, 
        "location": null, 
        "tokens": [
            "voting", 
            "hillary", 
            "clinton", 
            "equal", 
            "accelerating", 
            "muslim", 
            "killing", 
            "american"
        ], 
        "ht6": 0, 
        "ht5": 0, 
        "ht4": 0, 
        "ht3": 0, 
        "ht2": 1, 
        "ht1": 1, 
        "user_id": "715582132819664896", 
        "retweet_count": 0, 
        "id": 4190168997987024336, 
        "favorTrump": 2, 
        "ht8": 0
    }, 
    {
        "ht7": 0, 
        "againstTrump": 0, 
        "ranking_score": 0.5315802086110355, 
        "againstClinton": 1, 
        "text": "Wow DONALD TRUMP 2016 card #81 Rep. Presidential Finalist #MakeAmericaGreatAgain   #Trump #neverhillary https://t.co/iBB5IWbaCF via @eBay", 
        "created_at": "Sat Oct 01 08:08:28 +0000 2016", 
        "favorClinton": 0, 
        "location": "On EBay.com and EBid.net as: andy96961 and diamoundgirls", 
        "tokens": [
            "wow", 
            "donald", 
            "trump", 
            "2016", 
            "card", 
            "rep", 
            "presidential", 
            "finalist", 
            "via"
        ], 
        "ht6": 0, 
        "ht5": 0, 
        "ht4": 0, 
        "ht3": 0, 
        "ht2": 1, 
        "ht1": 0, 
        "user_id": "105781495", 
        "retweet_count": 0, 
        "id": 8758517476300352793, 
        "favorTrump": 1, 
        "ht8": 1
    }, 
    {
        "ht7": 0, 
        "againstTrump": 0, 
        "ranking_score": 0.591103260286561, 
        "againstClinton": 0, 
        "text": "RT @zvonko1976: This nails it - the best so far! #trump #lovetrumpshate #imwithher #hillaryclinton #election2016 #thisiseverything\u2026 ", 
        "created_at": "Sat Oct 01 08:08:43 +0000 2016", 
        "favorClinton": 1, 
        "location": "New York, USA", 
        "tokens": [
            "nail", 
            "best", 
            "far"
        ], 
        "ht6": 0, 
        "ht5": 0, 
        "ht4": 0, 
        "ht3": 1, 
        "ht2": 0, 
        "ht1": 0, 
        "user_id": "4046480597", 
        "retweet_count": 1, 
        "id": 8413817661373835023, 
        "favorTrump": 0, 
        "ht8": 0
    }, 
    {
        "ht7": 0, 
        "againstTrump": 0, 
        "ranking_score": 2.1202903849012684, 
        "againstClinton": 0, 
        "text": "RT @realkingrobbo: WHY YOU\u2019RE MENTALLY ILL IF YOU VOTE HILLARY CLINTON #crookedhillary #imwithher #TrumpTrain #Trump2016 #MAGA https://t.co\u2026", 
        "created_at": "Sat Oct 01 08:09:58 +0000 2016", 
        "favorClinton": 1, 
        "location": "South Pole", 
        "tokens": [
            "mentally", 
            "ill", 
            "vote", 
            "hillary", 
            "clinton"
        ], 
        "ht6": 0, 
        "ht5": 0, 
        "ht4": 0, 
        "ht3": 1, 
        "ht2": 0, 
        "ht1": 1, 
        "user_id": "2660660057", 
        "retweet_count": 19, 
        "id": 2087961598572198533, 
        "favorTrump": 1, 
        "ht8": 0
    }, 
    {
        "ht7": 0, 
        "againstTrump": 0, 
        "ranking_score": 0.1926289281505909, 
        "againstClinton": 0, 
        "text": "RT @amrightnow: #realdonaldtrump Boeing &amp; other Aircraft makers flock to Mexico https://t.co/WbsNTcuRVZ  @realDonaldTrump #trump2016 https:\u2026", 
        "created_at": "Sat Oct 01 08:10:42 +0000 2016", 
        "favorClinton": 0, 
        "location": null, 
        "tokens": [
            "boeing", 
            "amp", 
            "aircraft", 
            "maker", 
            "flock", 
            "mexico"
        ], 
        "ht6": 0, 
        "ht5": 0, 
        "ht4": 0, 
        "ht3": 0, 
        "ht2": 0, 
        "ht1": 1, 
        "user_id": "722699766598090752", 
        "retweet_count": 2, 
        "id": 5489513192137596866, 
        "favorTrump": 1, 
        "ht8": 0
    }, 
    {
        "ht7": 0, 
        "againstTrump": 0, 
        "ranking_score": 0.021919928866094382, 
        "againstClinton": 0, 
        "text": "#TrumpTrain Donald Trump #TrumpTrain 2016 Large Black Custom Decal IntlShip  #trump #trump2016 https://t.co/aGrO6GWCfO", 
        "created_at": "Sat Oct 01 08:10:53 +0000 2016", 
        "favorClinton": 0, 
        "location": null, 
        "tokens": [
            "donald", 
            "trump", 
            "2016", 
            "large", 
            "black", 
            "custom", 
            "decal", 
            "intlship"
        ], 
        "ht6": 0, 
        "ht5": 0, 
        "ht4": 0, 
        "ht3": 0, 
        "ht2": 0, 
        "ht1": 1, 
        "user_id": "771906755236401152", 
        "retweet_count": 0, 
        "id": 6927296935213087300, 
        "favorTrump": 1, 
        "ht8": 0
    }, 
    {
        "ht7": 0, 
        "againstTrump": 0, 
        "ranking_score": 1.3255208061689419, 
        "againstClinton": 0, 
        "text": "Bill Maher shreds Donald Trump\u2019s \"basket of inexplicables\" surrogates \u23e9 by @lee_moran https://t.co/9pXbM491YG via @HuffPostComedy#nevertrump", 
        "created_at": "Sat Oct 01 08:11:02 +0000 2016", 
        "favorClinton": 0, 
        "location": "Dearborn Heights, MI", 
        "tokens": [
            "bill", 
            "maher", 
            "shred", 
            "donald", 
            "trump", 
            "basket", 
            "inexplicables", 
            "surrogate", 
            "via"
        ], 
        "ht6": 0, 
        "ht5": 0, 
        "ht4": 0, 
        "ht3": 0, 
        "ht2": 0, 
        "ht1": 0, 
        "user_id": "770840445698080768", 
        "retweet_count": 0, 
        "id": 6826678493047206733, 
        "favorTrump": 0, 
        "ht8": 0
    }, 
    {
        "ht7": 0, 
        "againstTrump": 0, 
        "ranking_score": 0.1924565995335301, 
        "againstClinton": 0, 
        "text": "RT @amrightnow: #realdonaldtrump A Promise to Hillary #military #army #navy #usmc #airforce #veterans #trump #trumptrain #trump2016 https:/\u2026", 
        "created_at": "Sat Oct 01 08:11:20 +0000 2016", 
        "favorClinton": 0, 
        "location": null, 
        "tokens": [
            "promise", 
            "hillary"
        ], 
        "ht6": 0, 
        "ht5": 0, 
        "ht4": 0, 
        "ht3": 0, 
        "ht2": 0, 
        "ht1": 1, 
        "user_id": "722699766598090752", 
        "retweet_count": 2, 
        "id": 8750278932185542986, 
        "favorTrump": 1, 
        "ht8": 0
    }, 
    {
        "ht7": 0, 
        "againstTrump": 2, 
        "ranking_score": 4.919058380465577, 
        "againstClinton": 0, 
        "text": "US newspapers break with tradition to condemn 'dangerous demagogue' Donald Trump   https://t.co/zEiFGIAzQl\n#nevertrump\n#DumpTrump", 
        "created_at": "Sat Oct 01 08:12:23 +0000 2016", 
        "favorClinton": 0, 
        "location": null, 
        "tokens": [
            "newspaper", 
            "break", 
            "tradition", 
            "condemn", 
            "dangerous", 
            "demagogue", 
            "donald", 
            "trump"
        ], 
        "ht6": 1, 
        "ht5": 1, 
        "ht4": 0, 
        "ht3": 0, 
        "ht2": 0, 
        "ht1": 0, 
        "user_id": "2400099505", 
        "retweet_count": 0, 
        "id": 8363214524035210014, 
        "favorTrump": 0, 
        "ht8": 0
    }, 
    {
        "ht7": 0, 
        "againstTrump": 0, 
        "ranking_score": 3.0240099503578537, 
        "againstClinton": 0, 
        "text": "Trump aint having fun anymore but come so far he can't back down.. \nNow he's only option is to mess up! \nCongrats! \n#trump #imwithher", 
        "created_at": "Sat Oct 01 08:13:08 +0000 2016", 
        "favorClinton": 1, 
        "location": "G\u00f6teborg", 
        "tokens": [
            "trump", 
            "aint", 
            "fun", 
            "anymore", 
            "come", 
            "far", 
            "back", 
            "option", 
            "mess", 
            "congrats"
        ], 
        "ht6": 0, 
        "ht5": 0, 
        "ht4": 0, 
        "ht3": 1, 
        "ht2": 0, 
        "ht1": 0, 
        "user_id": "82850205", 
        "retweet_count": 0, 
        "id": 1494667064126540526, 
        "favorTrump": 0, 
        "ht8": 0
    }, 
    {
        "ht7": 0, 
        "againstTrump": 0, 
        "ranking_score": 3.363004593145881, 
        "againstClinton": 0, 
        "text": "RT @marchaig: BREAKING: \u201cTens of thousands\u201d of fraudulent Clinton votes found in Ohio warehouse\n\n#realdonaldtrump #trump2016 #maga https://\u2026", 
        "created_at": "Sat Oct 01 08:13:53 +0000 2016", 
        "favorClinton": 0, 
        "location": "Kentucky, USA", 
        "tokens": [
            "breaking", 
            "ten", 
            "thousand", 
            "fraudulent", 
            "clinton", 
            "vote", 
            "found", 
            "ohio", 
            "warehouse"
        ], 
        "ht6": 0, 
        "ht5": 0, 
        "ht4": 0, 
        "ht3": 0, 
        "ht2": 0, 
        "ht1": 1, 
        "user_id": "771378738491715584", 
        "retweet_count": 62, 
        "id": 1399331043372566051, 
        "favorTrump": 1, 
        "ht8": 0
    }, 
    {
        "ht7": 0, 
        "againstTrump": 0, 
        "ranking_score": 0.2561923218405893, 
        "againstClinton": 0, 
        "text": "@realDonaldTrump told me Hillary Clinton is honestly an innovative and focused veteran. https://t.co/fo7vdcydeu #hillaryclinton  #imwithher", 
        "created_at": "Sat Oct 01 08:15:18 +0000 2016", 
        "favorClinton": 1, 
        "location": "New York, NY", 
        "tokens": [
            "told", 
            "hillary", 
            "clinton", 
            "honestly", 
            "innovative", 
            "focused", 
            "veteran"
        ], 
        "ht6": 0, 
        "ht5": 0, 
        "ht4": 0, 
        "ht3": 1, 
        "ht2": 0, 
        "ht1": 0, 
        "user_id": "780177377980579840", 
        "retweet_count": 0, 
        "id": 6126391097536576244, 
        "favorTrump": 0, 
        "ht8": 0
    }, 
    {
        "ht7": 0, 
        "againstTrump": 0, 
        "ranking_score": 0.03845855720739662, 
        "againstClinton": 0, 
        "text": "\"The Real Trump\" Trump About You\" Watch Make #1 https://t.co/j58e8aacrE #tcot #pjnet #1A #2A #Trump #trump2016 https://t.co/NdK7TnCPPW", 
        "created_at": "Sat Oct 01 08:15:49 +0000 2016", 
        "favorClinton": 0, 
        "location": "New Jersey, USA", 
        "tokens": [
            "real", 
            "trump", 
            "trump", 
            "watch", 
            "make"
        ], 
        "ht6": 0, 
        "ht5": 0, 
        "ht4": 0, 
        "ht3": 0, 
        "ht2": 0, 
        "ht1": 1, 
        "user_id": "449110269", 
        "retweet_count": 0, 
        "id": 8345730778711581366, 
        "favorTrump": 1, 
        "ht8": 0
    }, 
    {
        "ht7": 0, 
        "againstTrump": 0, 
        "ranking_score": 0.03845799583650831, 
        "againstClinton": 0, 
        "text": "#realdonaldtrump A Promise to Hillary #military #army #navy #usmc #airforce #veterans #trump #trumptrain #trump2016 https://t.co/tLdvUZQdjs", 
        "created_at": "Sat Oct 01 08:16:00 +0000 2016", 
        "favorClinton": 0, 
        "location": "New Jersey, USA", 
        "tokens": [
            "promise", 
            "hillary"
        ], 
        "ht6": 0, 
        "ht5": 0, 
        "ht4": 0, 
        "ht3": 0, 
        "ht2": 0, 
        "ht1": 1, 
        "user_id": "449110269", 
        "retweet_count": 0, 
        "id": 7389535323210235821, 
        "favorTrump": 1, 
        "ht8": 0
    }, 
    {
        "ht7": 0, 
        "againstTrump": 1, 
        "ranking_score": 10.921590140268908, 
        "againstClinton": 0, 
        "text": "Well said!!! #nevertrump #Election2016 https://t.co/jwXV3LX8IS", 
        "created_at": "Sat Oct 01 08:16:43 +0000 2016", 
        "favorClinton": 0, 
        "location": null, 
        "tokens": [
            "well", 
            "said"
        ], 
        "ht6": 0, 
        "ht5": 1, 
        "ht4": 0, 
        "ht3": 0, 
        "ht2": 0, 
        "ht1": 0, 
        "user_id": "1304848968", 
        "retweet_count": 0, 
        "id": 6100623353747186756, 
        "favorTrump": 0, 
        "ht8": 0
    }, 
    {
        "ht7": 0, 
        "againstTrump": 0, 
        "ranking_score": 1.3882064912731593, 
        "againstClinton": 0, 
        "text": "based on his fib of an ad, @realDonaldTrump is for child labor, no health codes, illegal businesses... #imwithher", 
        "created_at": "Sat Oct 01 08:20:15 +0000 2016", 
        "favorClinton": 1, 
        "location": "L.A.", 
        "tokens": [
            "based", 
            "fib", 
            "child", 
            "labor", 
            "health", 
            "code", 
            "illegal", 
            "business"
        ], 
        "ht6": 0, 
        "ht5": 0, 
        "ht4": 0, 
        "ht3": 1, 
        "ht2": 0, 
        "ht1": 0, 
        "user_id": "17728106", 
        "retweet_count": 0, 
        "id": 2414017872614262231, 
        "favorTrump": 0, 
        "ht8": 0
    }, 
    {
        "ht7": 0, 
        "againstTrump": 0, 
        "ranking_score": 0.44851329019151165, 
        "againstClinton": 0, 
        "text": "A National Service Reserve is a great idea. Every country should do this! #civicresponsibility #imwithher https://t.co/SkzgkSZK9C", 
        "created_at": "Sat Oct 01 08:20:24 +0000 2016", 
        "favorClinton": 1, 
        "location": "Bloomsbury, London baby!", 
        "tokens": [
            "national", 
            "service", 
            "reserve", 
            "great", 
            "idea", 
            "every", 
            "country"
        ], 
        "ht6": 0, 
        "ht5": 0, 
        "ht4": 0, 
        "ht3": 1, 
        "ht2": 0, 
        "ht1": 0, 
        "user_id": "26458180", 
        "retweet_count": 0, 
        "id": 3336328845431304370, 
        "favorTrump": 0, 
        "ht8": 0
    }, 
    {
        "ht7": 0, 
        "againstTrump": 0, 
        "ranking_score": 4.805810524612601, 
        "againstClinton": 1, 
        "text": "@politico @HillaryClinton  Trump has proven that ANY man or woman can run for President NOT just the elites in the DC club! #neverhillary", 
        "created_at": "Sat Oct 01 08:20:33 +0000 2016", 
        "favorClinton": 0, 
        "location": null, 
        "tokens": [
            "trump", 
            "proven", 
            "man", 
            "woman", 
            "run", 
            "president", 
            "elite", 
            "club"
        ], 
        "ht6": 0, 
        "ht5": 0, 
        "ht4": 0, 
        "ht3": 0, 
        "ht2": 0, 
        "ht1": 0, 
        "user_id": "77674335", 
        "retweet_count": 0, 
        "id": 2951521435376585793, 
        "favorTrump": 0, 
        "ht8": 1
    }, 
    {
        "ht7": 0, 
        "againstTrump": 0, 
        "ranking_score": 0.013407194319931813, 
        "againstClinton": 0, 
        "text": "#TrumpInCuba Donald Trump #iPhone Case #TRUMP2016 #SWEET 5  #tcot #trump2016 https://t.co/CXR6TiuV7h", 
        "created_at": "Sat Oct 01 08:20:53 +0000 2016", 
        "favorClinton": 0, 
        "location": null, 
        "tokens": [
            "donald", 
            "trump", 
            "case"
        ], 
        "ht6": 0, 
        "ht5": 0, 
        "ht4": 0, 
        "ht3": 0, 
        "ht2": 0, 
        "ht1": 2, 
        "user_id": "771483365937676291", 
        "retweet_count": 0, 
        "id": 1213490875519222110, 
        "favorTrump": 2, 
        "ht8": 0
    }, 
    {
        "ht7": 0, 
        "againstTrump": 0, 
        "ranking_score": 0.18580369211983494, 
        "againstClinton": 0, 
        "text": "BILL CLINTON TAKES \"A DUMP\" ON AMERICA, THE CONGRESS, THE #FBI, and YOU MSM! #tcot #trump2016 #pjnet #TrumpTrain https://t.co/C8K2Y4dXfQ", 
        "created_at": "Sat Oct 01 08:21:04 +0000 2016", 
        "favorClinton": 0, 
        "location": "America", 
        "tokens": [
            "bill", 
            "clinton", 
            "take", 
            "dump", 
            "america", 
            "congress", 
            "msm"
        ], 
        "ht6": 0, 
        "ht5": 0, 
        "ht4": 0, 
        "ht3": 0, 
        "ht2": 0, 
        "ht1": 1, 
        "user_id": "292263105", 
        "retweet_count": 0, 
        "id": 4011784897404022271, 
        "favorTrump": 1, 
        "ht8": 0
    }, 
    {
        "ht7": 0, 
        "againstTrump": 0, 
        "ranking_score": 0.9076946898805193, 
        "againstClinton": 1, 
        "text": "RT @themouthmatusow: Followcmy buddy @Cernovich we speak the truth on whats truly happening #neverhillary https://t.co/6homEFYwhG", 
        "created_at": "Sat Oct 01 08:21:56 +0000 2016", 
        "favorClinton": 0, 
        "location": "Muldrow, OK", 
        "tokens": [
            "followcmy", 
            "buddy", 
            "speak", 
            "truth", 
            "whats", 
            "truly", 
            "happening"
        ], 
        "ht6": 0, 
        "ht5": 0, 
        "ht4": 0, 
        "ht3": 0, 
        "ht2": 0, 
        "ht1": 0, 
        "user_id": "1554397106", 
        "retweet_count": 86, 
        "id": 6655816071459282371, 
        "favorTrump": 0, 
        "ht8": 1
    }, 
    {
        "ht7": 0, 
        "againstTrump": 0, 
        "ranking_score": 0.4585604141644491, 
        "againstClinton": 0, 
        "text": "RT @realkingrobbo: WHY YOU\u2019RE MENTALLY ILL IF YOU VOTE HILLARY CLINTON #crookedhillary #imwithher #TrumpTrain #Trump2016 #MAGA https://t.co\u2026", 
        "created_at": "Sat Oct 01 08:23:13 +0000 2016", 
        "favorClinton": 1, 
        "location": null, 
        "tokens": [
            "mentally", 
            "ill", 
            "vote", 
            "hillary", 
            "clinton"
        ], 
        "ht6": 0, 
        "ht5": 0, 
        "ht4": 0, 
        "ht3": 1, 
        "ht2": 0, 
        "ht1": 1, 
        "user_id": "3257260730", 
        "retweet_count": 20, 
        "id": 3032266286850159211, 
        "favorTrump": 1, 
        "ht8": 0
    }, 
    {
        "ht7": 0, 
        "againstTrump": 1, 
        "ranking_score": 1.589950975447634, 
        "againstClinton": 0, 
        "text": "@realDonaldTrump says \"I can be nastier than she ever can be\" No one doubts that.  #nevertrump #Hillary2016", 
        "created_at": "Sat Oct 01 08:23:48 +0000 2016", 
        "favorClinton": 1, 
        "location": null, 
        "tokens": [
            "say", 
            "nastier", 
            "ever", 
            "one", 
            "doubt"
        ], 
        "ht6": 0, 
        "ht5": 1, 
        "ht4": 1, 
        "ht3": 0, 
        "ht2": 0, 
        "ht1": 0, 
        "user_id": "772741976051617792", 
        "retweet_count": 0, 
        "id": 8331942730751110968, 
        "favorTrump": 0, 
        "ht8": 0
    }, 
    {
        "ht7": 0, 
        "againstTrump": 0, 
        "ranking_score": 1.609462448835509, 
        "againstClinton": 0, 
        "text": "@realDonaldTrump Phew!  Looks like the guy whose job it is to take DT's phone away is back on duty tonight.  #imwithher #StrongerTogether", 
        "created_at": "Sat Oct 01 08:28:02 +0000 2016", 
        "favorClinton": 1, 
        "location": null, 
        "tokens": [
            "phew", 
            "look", 
            "like", 
            "guy", 
            "whose", 
            "job", 
            "take", 
            "phone", 
            "away", 
            "back", 
            "duty", 
            "tonight"
        ], 
        "ht6": 0, 
        "ht5": 0, 
        "ht4": 0, 
        "ht3": 1, 
        "ht2": 0, 
        "ht1": 0, 
        "user_id": "32558095", 
        "retweet_count": 0, 
        "id": 1258911575358779412, 
        "favorTrump": 0, 
        "ht8": 0
    }, 
    {
        "ht7": 0, 
        "againstTrump": 1, 
        "ranking_score": 0.37375693696084444, 
        "againstClinton": 0, 
        "text": "RT @BenHowe: Every time Trump is quiet &amp; doing ok, Trump supporters are cocky &amp; dismissive of #nevertrump. \n\nWhen he fucks up? We're making\u2026", 
        "created_at": "Sat Oct 01 08:29:55 +0000 2016", 
        "favorClinton": 0, 
        "location": null, 
        "tokens": [
            "every", 
            "time", 
            "trump", 
            "quiet", 
            "amp", 
            "trump", 
            "supporter", 
            "cocky", 
            "amp", 
            "dismissive", 
            "fuck", 
            "making"
        ], 
        "ht6": 0, 
        "ht5": 1, 
        "ht4": 0, 
        "ht3": 0, 
        "ht2": 0, 
        "ht1": 0, 
        "user_id": "708070902911651840", 
        "retweet_count": 151, 
        "id": 574112323878719826, 
        "favorTrump": 0, 
        "ht8": 0
    }, 
    {
        "ht7": 0, 
        "againstTrump": 0, 
        "ranking_score": 1.3990247676488565, 
        "againstClinton": 0, 
        "text": "RT @marchaig: BREAKING: \u201cTens of thousands\u201d of fraudulent Clinton votes found in Ohio warehouse\n\n#realdonaldtrump #trump2016 #maga https://\u2026", 
        "created_at": "Sat Oct 01 08:29:56 +0000 2016", 
        "favorClinton": 0, 
        "location": "USA", 
        "tokens": [
            "breaking", 
            "ten", 
            "thousand", 
            "fraudulent", 
            "clinton", 
            "vote", 
            "found", 
            "ohio", 
            "warehouse"
        ], 
        "ht6": 0, 
        "ht5": 0, 
        "ht4": 0, 
        "ht3": 0, 
        "ht2": 0, 
        "ht1": 1, 
        "user_id": "22037009", 
        "retweet_count": 63, 
        "id": 4635910238529871294, 
        "favorTrump": 1, 
        "ht8": 0
    }, 
    {
        "ht7": 0, 
        "againstTrump": 0, 
        "ranking_score": 0.05388214622654895, 
        "againstClinton": 0, 
        "text": "\"The Real Trump\" Trump About You\" Watch Make #1 https://t.co/QK2MC9wQjR #tcot #pjnet #1A #2A #Trump #trump2016 https://t.co/fqutZVEjlg", 
        "created_at": "Sat Oct 01 08:31:18 +0000 2016", 
        "favorClinton": 0, 
        "location": null, 
        "tokens": [
            "real", 
            "trump", 
            "trump", 
            "watch", 
            "make"
        ], 
        "ht6": 0, 
        "ht5": 0, 
        "ht4": 0, 
        "ht3": 0, 
        "ht2": 0, 
        "ht1": 1, 
        "user_id": "4541034916", 
        "retweet_count": 0, 
        "id": 3419702518560047949, 
        "favorTrump": 1, 
        "ht8": 0
    }, 
    {
        "ht7": 0, 
        "againstTrump": 1, 
        "ranking_score": 1.2930060516843451, 
        "againstClinton": 0, 
        "text": "Don't hold your nose and vote for Trump this November, the stink will linger for ever America. #countryBeforeParty. #nevertrump", 
        "created_at": "Sat Oct 01 08:31:20 +0000 2016", 
        "favorClinton": 0, 
        "location": null, 
        "tokens": [
            "hold", 
            "nose", 
            "vote", 
            "trump", 
            "november", 
            "stink", 
            "linger", 
            "ever", 
            "america"
        ], 
        "ht6": 0, 
        "ht5": 1, 
        "ht4": 0, 
        "ht3": 0, 
        "ht2": 0, 
        "ht1": 0, 
        "user_id": "711033891944054785", 
        "retweet_count": 0, 
        "id": 864844245149641375, 
        "favorTrump": 0, 
        "ht8": 0
    }, 
    {
        "ht7": 0, 
        "againstTrump": 0, 
        "ranking_score": 0.5315636422869078, 
        "againstClinton": 1, 
        "text": "RT @AndreaQtown: Wow DONALD TRUMP 2016 card #81 Rep. Presidential Finalist #MakeAmericaGreatAgain   #Trump #neverhillary https://t.co/iBB5I\u2026", 
        "created_at": "Sat Oct 01 08:32:45 +0000 2016", 
        "favorClinton": 0, 
        "location": "On EBay.com and EBid.net as: andy96961 and diamoundgirls", 
        "tokens": [
            "wow", 
            "donald", 
            "trump", 
            "2016", 
            "card", 
            "rep", 
            "presidential", 
            "finalist"
        ], 
        "ht6": 0, 
        "ht5": 0, 
        "ht4": 0, 
        "ht3": 0, 
        "ht2": 1, 
        "ht1": 0, 
        "user_id": "105781495", 
        "retweet_count": 1, 
        "id": 5859341755052094207, 
        "favorTrump": 1, 
        "ht8": 1
    }, 
    {
        "ht7": 0, 
        "againstTrump": 0, 
        "ranking_score": 0.18579945713306345, 
        "againstClinton": 0, 
        "text": "World trade leaders dread a TRUMP presidency, LIBERALS think this is a BAD THING?\nhttps://t.co/JaZi60DGQj #trump2016 #tcot #pjnet #BBC #UK", 
        "created_at": "Sat Oct 01 08:33:14 +0000 2016", 
        "favorClinton": 0, 
        "location": "America", 
        "tokens": [
            "world", 
            "trade", 
            "leader", 
            "dread", 
            "trump", 
            "presidency", 
            "liberal", 
            "think", 
            "bad", 
            "thing"
        ], 
        "ht6": 0, 
        "ht5": 0, 
        "ht4": 0, 
        "ht3": 0, 
        "ht2": 0, 
        "ht1": 1, 
        "user_id": "292263105", 
        "retweet_count": 0, 
        "id": 8183425091423420154, 
        "favorTrump": 1, 
        "ht8": 0
    }, 
    {
        "ht7": 0, 
        "againstTrump": 1, 
        "ranking_score": 0.25565635464008596, 
        "againstClinton": 0, 
        "text": "Analysts say Hillary Clinton is positively a passionate and astute lover of humanity. https://t.co/578wVVK575 #nevertrump", 
        "created_at": "Sat Oct 01 08:35:18 +0000 2016", 
        "favorClinton": 0, 
        "location": "New York, NY", 
        "tokens": [
            "analyst", 
            "say", 
            "hillary", 
            "clinton", 
            "positively", 
            "passionate", 
            "astute", 
            "lover", 
            "humanity"
        ], 
        "ht6": 0, 
        "ht5": 1, 
        "ht4": 0, 
        "ht3": 0, 
        "ht2": 0, 
        "ht1": 0, 
        "user_id": "780177377980579840", 
        "retweet_count": 0, 
        "id": 850942313773364352, 
        "favorTrump": 0, 
        "ht8": 0
    }, 
    {
        "ht7": 0, 
        "againstTrump": 0, 
        "ranking_score": 0.04832515925063226, 
        "againstClinton": 0, 
        "text": "#TrumpInCuba Donald Trump #TrumpTrain 2016  Large White Custom Decal IntlShip  #tpp #sgp #trump2016 https://t.co/4e0YjWABrA", 
        "created_at": "Sat Oct 01 08:35:53 +0000 2016", 
        "favorClinton": 0, 
        "location": null, 
        "tokens": [
            "donald", 
            "trump", 
            "2016", 
            "large", 
            "white", 
            "custom", 
            "decal", 
            "intlship"
        ], 
        "ht6": 0, 
        "ht5": 0, 
        "ht4": 0, 
        "ht3": 0, 
        "ht2": 0, 
        "ht1": 1, 
        "user_id": "780159670585593856", 
        "retweet_count": 0, 
        "id": 4991607009906413176, 
        "favorTrump": 1, 
        "ht8": 0
    }, 
    {
        "ht7": 0, 
        "againstTrump": 1, 
        "ranking_score": 0.3901695458521185, 
        "againstClinton": 0, 
        "text": "#dumptrump and build a fence around him! #Trump", 
        "created_at": "Sat Oct 01 08:36:28 +0000 2016", 
        "favorClinton": 0, 
        "location": "Troll @ ur own risk!", 
        "tokens": [
            "build", 
            "fence", 
            "around"
        ], 
        "ht6": 1, 
        "ht5": 0, 
        "ht4": 0, 
        "ht3": 0, 
        "ht2": 0, 
        "ht1": 0, 
        "user_id": "29511206", 
        "retweet_count": 0, 
        "id": 3119737983851167636, 
        "favorTrump": 0, 
        "ht8": 0
    }, 
    {
        "ht7": 0, 
        "againstTrump": 1, 
        "ranking_score": 0.5167124100515622, 
        "againstClinton": 0, 
        "text": "Body Language says everything. \n#nevertrump https://t.co/CIuABkQd4v", 
        "created_at": "Sat Oct 01 08:36:40 +0000 2016", 
        "favorClinton": 0, 
        "location": "Colorado, USA", 
        "tokens": [
            "body", 
            "language", 
            "say", 
            "everything"
        ], 
        "ht6": 0, 
        "ht5": 1, 
        "ht4": 0, 
        "ht3": 0, 
        "ht2": 0, 
        "ht1": 0, 
        "user_id": "2329440216", 
        "retweet_count": 0, 
        "id": 4264865032936354511, 
        "favorTrump": 0, 
        "ht8": 0
    }, 
    {
        "ht7": 0, 
        "againstTrump": 0, 
        "ranking_score": 0.36158840799469044, 
        "againstClinton": 1, 
        "text": "RT @VolkerChristina: Hilary Clinton Pay to Play proof per #DNCleak #neverhillary #TrumpPence16 \ud83c\uddfa\ud83c\uddf8 https://t.co/unwWTDa2Sr", 
        "created_at": "Sat Oct 01 08:39:53 +0000 2016", 
        "favorClinton": 0, 
        "location": "New York, California & Florida", 
        "tokens": [
            "hilary", 
            "clinton", 
            "pay", 
            "play", 
            "proof", 
            "per"
        ], 
        "ht6": 0, 
        "ht5": 0, 
        "ht4": 0, 
        "ht3": 0, 
        "ht2": 0, 
        "ht1": 0, 
        "user_id": "853766604", 
        "retweet_count": 48, 
        "id": 7763727951668036258, 
        "favorTrump": 0, 
        "ht8": 1
    }, 
    {
        "ht7": 0, 
        "againstTrump": 0, 
        "ranking_score": 0.39131283175634635, 
        "againstClinton": 0, 
        "text": "RT @realkingrobbo: WHY YOU\u2019RE MENTALLY ILL IF YOU VOTE HILLARY CLINTON #crookedhillary #imwithher #TrumpTrain #Trump2016 #MAGA https://t.co\u2026", 
        "created_at": "Sat Oct 01 08:40:15 +0000 2016", 
        "favorClinton": 1, 
        "location": null, 
        "tokens": [
            "mentally", 
            "ill", 
            "vote", 
            "hillary", 
            "clinton"
        ], 
        "ht6": 0, 
        "ht5": 0, 
        "ht4": 0, 
        "ht3": 1, 
        "ht2": 0, 
        "ht1": 1, 
        "user_id": "249504637", 
        "retweet_count": 21, 
        "id": 7863910202264942673, 
        "favorTrump": 1, 
        "ht8": 0
    }, 
    {
        "ht7": 0, 
        "againstTrump": 0, 
        "ranking_score": 0.2855424941803596, 
        "againstClinton": 0, 
        "text": "RT @realkingrobbo: WHY YOU\u2019RE MENTALLY ILL IF YOU VOTE HILLARY CLINTON #crookedhillary #imwithher #TrumpTrain #Trump2016 #MAGA https://t.co\u2026", 
        "created_at": "Sat Oct 01 08:40:38 +0000 2016", 
        "favorClinton": 1, 
        "location": null, 
        "tokens": [
            "mentally", 
            "ill", 
            "vote", 
            "hillary", 
            "clinton"
        ], 
        "ht6": 0, 
        "ht5": 0, 
        "ht4": 0, 
        "ht3": 1, 
        "ht2": 0, 
        "ht1": 1, 
        "user_id": "2242421732", 
        "retweet_count": 22, 
        "id": 3109954808649525299, 
        "favorTrump": 1, 
        "ht8": 0
    }, 
    {
        "ht7": 0, 
        "againstTrump": 0, 
        "ranking_score": 0.18663315482428847, 
        "againstClinton": 0, 
        "text": "RT @Trumptowin1: https://t.co/Zu3t5ha8cd\nShe is sick . #trump #trump2016", 
        "created_at": "Sat Oct 01 08:42:31 +0000 2016", 
        "favorClinton": 0, 
        "location": "Gulfport, MS 39507", 
        "tokens": [
            "sick"
        ], 
        "ht6": 0, 
        "ht5": 0, 
        "ht4": 0, 
        "ht3": 0, 
        "ht2": 0, 
        "ht1": 1, 
        "user_id": "1109949931", 
        "retweet_count": 7, 
        "id": 8635806410386210584, 
        "favorTrump": 1, 
        "ht8": 0
    }, 
    {
        "ht7": 0, 
        "againstTrump": 0, 
        "ranking_score": 0.7818473746330886, 
        "againstClinton": 0, 
        "text": "@HillaryClinton You go Girl! #imwithher", 
        "created_at": "Sat Oct 01 08:43:18 +0000 2016", 
        "favorClinton": 1, 
        "location": null, 
        "tokens": [
            "girl"
        ], 
        "ht6": 0, 
        "ht5": 0, 
        "ht4": 0, 
        "ht3": 1, 
        "ht2": 0, 
        "ht1": 0, 
        "user_id": "762340949716570112", 
        "retweet_count": 0, 
        "id": 5101737282236791055, 
        "favorTrump": 0, 
        "ht8": 0
    }, 
    {
        "ht7": 0, 
        "againstTrump": 0, 
        "ranking_score": 1.0897123014256194, 
        "againstClinton": 0, 
        "text": "RT @pepesgrandma: Don't count on free college, Hillary lied again.  Audio proof! #maga #trump #bernieorbust #imwithher\u2026 ", 
        "created_at": "Sat Oct 01 08:44:41 +0000 2016", 
        "favorClinton": 1, 
        "location": null, 
        "tokens": [
            "count", 
            "free", 
            "college", 
            "hillary", 
            "lied", 
            "audio", 
            "proof"
        ], 
        "ht6": 0, 
        "ht5": 0, 
        "ht4": 0, 
        "ht3": 1, 
        "ht2": 0, 
        "ht1": 0, 
        "user_id": "95186905", 
        "retweet_count": 23, 
        "id": 4910895815945086761, 
        "favorTrump": 0, 
        "ht8": 0
    }, 
    {
        "ht7": 0, 
        "againstTrump": 1, 
        "ranking_score": 0.25461972271163236, 
        "againstClinton": 0, 
        "text": "@KingJames told me Mrs. Clinton is without a doubt a gutsy and cool-headed politician. Sounds pretty good to me! #nevertrump", 
        "created_at": "Sat Oct 01 08:45:18 +0000 2016", 
        "favorClinton": 0, 
        "location": "New York, NY", 
        "tokens": [
            "told", 
            "clinton", 
            "without", 
            "doubt", 
            "gutsy", 
            "coolheaded", 
            "politician", 
            "sound", 
            "pretty", 
            "good"
        ], 
        "ht6": 0, 
        "ht5": 1, 
        "ht4": 0, 
        "ht3": 0, 
        "ht2": 0, 
        "ht1": 0, 
        "user_id": "780177377980579840", 
        "retweet_count": 0, 
        "id": 1073901742616845510, 
        "favorTrump": 0, 
        "ht8": 0
    }, 
    {
        "ht7": 0, 
        "againstTrump": 0, 
        "ranking_score": 0.038455225720000236, 
        "againstClinton": 0, 
        "text": "realdonaldtrump No Trust Hillary #military #army #navy #usmc #airforce #veterans #trump #trumptrain #trump2016 https://t.co/bbflMDHCSP", 
        "created_at": "Sat Oct 01 08:45:49 +0000 2016", 
        "favorClinton": 0, 
        "location": "New Jersey, USA", 
        "tokens": [
            "realdonaldtrump", 
            "trust", 
            "hillary"
        ], 
        "ht6": 0, 
        "ht5": 0, 
        "ht4": 0, 
        "ht3": 0, 
        "ht2": 0, 
        "ht1": 1, 
        "user_id": "449110269", 
        "retweet_count": 0, 
        "id": 5200299952064815979, 
        "favorTrump": 1, 
        "ht8": 0
    }, 
    {
        "ht7": 0, 
        "againstTrump": 0, 
        "ranking_score": 0.05387876559811927, 
        "againstClinton": 0, 
        "text": "\"The Real Trump\" Trump About You\" Watch Make #1 https://t.co/QK2MC9wQjR  #tcot #pjnet #1A #2A #Trump #trump2016 https://t.co/ILIOiSO8f6", 
        "created_at": "Sat Oct 01 08:46:15 +0000 2016", 
        "favorClinton": 0, 
        "location": null, 
        "tokens": [
            "real", 
            "trump", 
            "trump", 
            "watch", 
            "make"
        ], 
        "ht6": 0, 
        "ht5": 0, 
        "ht4": 0, 
        "ht3": 0, 
        "ht2": 0, 
        "ht1": 1, 
        "user_id": "4541034916", 
        "retweet_count": 0, 
        "id": 5782248615908696907, 
        "favorTrump": 1, 
        "ht8": 0
    }, 
    {
        "ht7": 0, 
        "againstTrump": 0, 
        "ranking_score": 0.407079641847888, 
        "againstClinton": 0, 
        "text": "RT @amrightnow: realdonaldtrump No Trust Hillary #military #army #navy #usmc #airforce #veterans #trump #trumptrain #trump2016 https://t.co\u2026", 
        "created_at": "Sat Oct 01 08:47:38 +0000 2016", 
        "favorClinton": 0, 
        "location": null, 
        "tokens": [
            "realdonaldtrump", 
            "trust", 
            "hillary"
        ], 
        "ht6": 0, 
        "ht5": 0, 
        "ht4": 0, 
        "ht3": 0, 
        "ht2": 0, 
        "ht1": 1, 
        "user_id": "54251487", 
        "retweet_count": 1, 
        "id": 506833159935320013, 
        "favorTrump": 1, 
        "ht8": 0
    }, 
    {
        "ht7": 0, 
        "againstTrump": 0, 
        "ranking_score": 0.08277441623464736, 
        "againstClinton": 0, 
        "text": "Ford to build huge plant in Mexico despite outrage https://t.co/4qMisWjvwX #realDonaldTrump #trump2016 #maga https://t.co/FItSKh5bJR", 
        "created_at": "Sat Oct 01 08:48:03 +0000 2016", 
        "favorClinton": 0, 
        "location": "USA", 
        "tokens": [
            "ford", 
            "build", 
            "huge", 
            "plant", 
            "mexico", 
            "despite", 
            "outrage"
        ], 
        "ht6": 0, 
        "ht5": 0, 
        "ht4": 0, 
        "ht3": 0, 
        "ht2": 0, 
        "ht1": 1, 
        "user_id": "4081892233", 
        "retweet_count": 0, 
        "id": 8866312821854254384, 
        "favorTrump": 1, 
        "ht8": 0
    }, 
    {
        "ht7": 0, 
        "againstTrump": 0, 
        "ranking_score": 0.1684546547244163, 
        "againstClinton": 0, 
        "text": "RT @pepesgrandma: Don't count on free college, Hillary lied again.  Audio proof! #maga #trump #bernieorbust #imwithher\u2026 ", 
        "created_at": "Sat Oct 01 08:48:59 +0000 2016", 
        "favorClinton": 1, 
        "location": "Sunny Coast", 
        "tokens": [
            "count", 
            "free", 
            "college", 
            "hillary", 
            "lied", 
            "audio", 
            "proof"
        ], 
        "ht6": 0, 
        "ht5": 0, 
        "ht4": 0, 
        "ht3": 1, 
        "ht2": 0, 
        "ht1": 0, 
        "user_id": "349445673", 
        "retweet_count": 24, 
        "id": 3277603929326961285, 
        "favorTrump": 0, 
        "ht8": 0
    }, 
    {
        "ht7": 0, 
        "againstTrump": 0, 
        "ranking_score": 4.788775355364269, 
        "againstClinton": 1, 
        "text": "RT Bill Clinton's Affairs and Assaults\n#neverhillary https://t.co/ieStgJTv1w", 
        "created_at": "Sat Oct 01 08:49:36 +0000 2016", 
        "favorClinton": 0, 
        "location": null, 
        "tokens": [
            "bill", 
            "clinton", 
            "affair", 
            "assault"
        ], 
        "ht6": 0, 
        "ht5": 0, 
        "ht4": 0, 
        "ht3": 0, 
        "ht2": 0, 
        "ht1": 0, 
        "user_id": "77674335", 
        "retweet_count": 0, 
        "id": 4287281728052565829, 
        "favorTrump": 0, 
        "ht8": 1
    }, 
    {
        "ht7": 0, 
        "againstTrump": 0, 
        "ranking_score": 1.1573577570818014, 
        "againstClinton": 0, 
        "text": "RT @TrumpedAmerica: Ford to build huge plant in Mexico despite outrage https://t.co/4qMisWjvwX #realDonaldTrump #trump2016 #maga https://t.\u2026", 
        "created_at": "Sat Oct 01 08:49:36 +0000 2016", 
        "favorClinton": 0, 
        "location": "Vero Beach, FL", 
        "tokens": [
            "ford", 
            "build", 
            "huge", 
            "plant", 
            "mexico", 
            "despite", 
            "outrage"
        ], 
        "ht6": 0, 
        "ht5": 0, 
        "ht4": 0, 
        "ht3": 0, 
        "ht2": 0, 
        "ht1": 1, 
        "user_id": "2405538056", 
        "retweet_count": 1, 
        "id": 6474710530351814064, 
        "favorTrump": 1, 
        "ht8": 0
    }, 
    {
        "ht7": 0, 
        "againstTrump": 1, 
        "ranking_score": 6.050856528157018, 
        "againstClinton": 1, 
        "text": "Women who know Trump defend the GOP candidate's character https://t.co/i0MnI3e33E  #neverhillary #nevertrump", 
        "created_at": "Sat Oct 01 08:50:00 +0000 2016", 
        "favorClinton": 0, 
        "location": "Narnia", 
        "tokens": [
            "woman", 
            "know", 
            "trump", 
            "defend", 
            "gop", 
            "candidate", 
            "character"
        ], 
        "ht6": 0, 
        "ht5": 1, 
        "ht4": 0, 
        "ht3": 0, 
        "ht2": 0, 
        "ht1": 0, 
        "user_id": "61393631", 
        "retweet_count": 0, 
        "id": 794959613972096821, 
        "favorTrump": 0, 
        "ht8": 1
    }, 
    {
        "ht7": 0, 
        "againstTrump": 0, 
        "ranking_score": 0.04823071268532157, 
        "againstClinton": 0, 
        "text": "#TrumpWon Donald Trump #TrumpHead Large Black Custom Decal IntlShip  #tpp #tpp #trump2016 https://t.co/SPlK8nyXJQ", 
        "created_at": "Sat Oct 01 08:50:54 +0000 2016", 
        "favorClinton": 0, 
        "location": null, 
        "tokens": [
            "donald", 
            "trump", 
            "large", 
            "black", 
            "custom", 
            "decal", 
            "intlship"
        ], 
        "ht6": 0, 
        "ht5": 0, 
        "ht4": 0, 
        "ht3": 0, 
        "ht2": 0, 
        "ht1": 1, 
        "user_id": "780159670585593856", 
        "retweet_count": 0, 
        "id": 1400399339719401845, 
        "favorTrump": 1, 
        "ht8": 0
    }, 
    {
        "ht7": 0, 
        "againstTrump": 0, 
        "ranking_score": 0.1562256710698929, 
        "againstClinton": 0, 
        "text": "Donald Trump praised Shariah law in Saudi Arabia https://t.co/qkcb625JK8 #imwithher #uniteblue #trump2016 #trumptrain @MotherJones", 
        "created_at": "Sat Oct 01 08:51:09 +0000 2016", 
        "favorClinton": 1, 
        "location": "Over There", 
        "tokens": [
            "donald", 
            "trump", 
            "praised", 
            "shariah", 
            "law", 
            "saudi", 
            "arabia"
        ], 
        "ht6": 0, 
        "ht5": 0, 
        "ht4": 0, 
        "ht3": 1, 
        "ht2": 0, 
        "ht1": 1, 
        "user_id": "318073012", 
        "retweet_count": 0, 
        "id": 2499619361231093675, 
        "favorTrump": 1, 
        "ht8": 0
    }, 
    {
        "ht7": 0, 
        "againstTrump": 0, 
        "ranking_score": 0.15860316507641112, 
        "againstClinton": 0, 
        "text": "RT @KatrinaPierson: Notice how @CNN pretends that this never happened? #trump2016 #maga https://t.co/Xr77GuwfFS", 
        "created_at": "Sat Oct 01 08:51:18 +0000 2016", 
        "favorClinton": 0, 
        "location": "Riverside, CA", 
        "tokens": [
            "notice", 
            "pretend", 
            "never", 
            "happened"
        ], 
        "ht6": 0, 
        "ht5": 0, 
        "ht4": 0, 
        "ht3": 0, 
        "ht2": 0, 
        "ht1": 1, 
        "user_id": "703095412652011521", 
        "retweet_count": 3630, 
        "id": 2284494651058382858, 
        "favorTrump": 1, 
        "ht8": 0
    }, 
    {
        "ht7": 0, 
        "againstTrump": 0, 
        "ranking_score": 1.1615504017800375, 
        "againstClinton": 0, 
        "text": "RT @freelancewoman: Donald Trump praised Shariah law in Saudi Arabia https://t.co/qkcb625JK8 #imwithher #uniteblue #trump2016 #trumptrain @\u2026", 
        "created_at": "Sat Oct 01 08:52:24 +0000 2016", 
        "favorClinton": 1, 
        "location": null, 
        "tokens": [
            "donald", 
            "trump", 
            "praised", 
            "shariah", 
            "law", 
            "saudi", 
            "arabia"
        ], 
        "ht6": 0, 
        "ht5": 0, 
        "ht4": 0, 
        "ht3": 1, 
        "ht2": 0, 
        "ht1": 1, 
        "user_id": "602001679", 
        "retweet_count": 1, 
        "id": 8637722120065804736, 
        "favorTrump": 1, 
        "ht8": 0
    }, 
    {
        "ht7": 0, 
        "againstTrump": 0, 
        "ranking_score": 0.3262431946007657, 
        "againstClinton": 0, 
        "text": "#Trump2016  #makeamericagreatagain Sanders surrogate, Ben  https://t.co/eiVaiz6PBk", 
        "created_at": "Sat Oct 01 08:53:26 +0000 2016", 
        "favorClinton": 0, 
        "location": null, 
        "tokens": [
            "sander", 
            "surrogate", 
            "ben"
        ], 
        "ht6": 0, 
        "ht5": 0, 
        "ht4": 0, 
        "ht3": 0, 
        "ht2": 1, 
        "ht1": 1, 
        "user_id": "715582132819664896", 
        "retweet_count": 0, 
        "id": 3248019045054183409, 
        "favorTrump": 2, 
        "ht8": 0
    }, 
    {
        "ht7": 0, 
        "againstTrump": 0, 
        "ranking_score": 10.86562098660699, 
        "againstClinton": 0, 
        "text": "Trump should strip down 2 his skivvies &amp;show us what he's working w/b4 critiquing someone else's physique #frumpytrumpy #fatcat #hillary2016", 
        "created_at": "Sat Oct 01 08:53:26 +0000 2016", 
        "favorClinton": 1, 
        "location": "Philadelphia, PA", 
        "tokens": [
            "trump", 
            "strip", 
            "skivvy", 
            "amp", 
            "show", 
            "working", 
            "wb4", 
            "critiquing", 
            "someone", 
            "else", 
            "physique"
        ], 
        "ht6": 0, 
        "ht5": 0, 
        "ht4": 1, 
        "ht3": 0, 
        "ht2": 0, 
        "ht1": 0, 
        "user_id": "33763169", 
        "retweet_count": 0, 
        "id": 1312130210488217445, 
        "favorTrump": 0, 
        "ht8": 0
    }, 
    {
        "ht7": 0, 
        "againstTrump": 0, 
        "ranking_score": 4.7868900107361725, 
        "againstClinton": 1, 
        "text": "1993 Chelsea Clinton's Nanny lands a $20,000 job at the WH. Hmmm #neverhillary\nhttps://t.co/kRpkfyC9M0", 
        "created_at": "Sat Oct 01 08:54:04 +0000 2016", 
        "favorClinton": 0, 
        "location": null, 
        "tokens": [
            "1993", 
            "chelsea", 
            "clinton", 
            "nanny", 
            "land", 
            "20000", 
            "job", 
            "hmmm"
        ], 
        "ht6": 0, 
        "ht5": 0, 
        "ht4": 0, 
        "ht3": 0, 
        "ht2": 0, 
        "ht1": 0, 
        "user_id": "77674335", 
        "retweet_count": 0, 
        "id": 2558335923833097391, 
        "favorTrump": 0, 
        "ht8": 1
    }, 
    {
        "ht7": 0, 
        "againstTrump": 0, 
        "ranking_score": 0.1976869413501863, 
        "againstClinton": 0, 
        "text": "While Hillary &amp; MSM obsess over a porn star, @realDonaldTrump focuses on helping moms.\n\nhttps://t.co/9cZJBfKwRZ\n#trump2016 #TrumpTrain #MAGA", 
        "created_at": "Sat Oct 01 08:54:28 +0000 2016", 
        "favorClinton": 0, 
        "location": "Raleigh, NC", 
        "tokens": [
            "hillary", 
            "amp", 
            "msm", 
            "porn", 
            "star", 
            "focus", 
            "helping", 
            "mom"
        ], 
        "ht6": 0, 
        "ht5": 0, 
        "ht4": 0, 
        "ht3": 0, 
        "ht2": 0, 
        "ht1": 1, 
        "user_id": "4175166177", 
        "retweet_count": 0, 
        "id": 5471197603171898380, 
        "favorTrump": 1, 
        "ht8": 0
    }, 
    {
        "ht7": 0, 
        "againstTrump": 1, 
        "ranking_score": 0.05208301651799528, 
        "againstClinton": 0, 
        "text": "#TrumpInCuba Gary Johnson on Donald TrumpTax Release #NeverTrump  #ccot #trump2016 https://t.co/twrLSYlLSz", 
        "created_at": "Sat Oct 01 08:55:53 +0000 2016", 
        "favorClinton": 0, 
        "location": null, 
        "tokens": [
            "gary", 
            "johnson", 
            "donald", 
            "trumptax", 
            "release"
        ], 
        "ht6": 0, 
        "ht5": 1, 
        "ht4": 0, 
        "ht3": 0, 
        "ht2": 0, 
        "ht1": 1, 
        "user_id": "779870855836729344", 
        "retweet_count": 0, 
        "id": 1415137643346344426, 
        "favorTrump": 1, 
        "ht8": 0
    }
]